ellapycount/__init__.py
ellapycount/ellapycount.py
ellapycount/plotting.py
ellapycount-0.1.0.dist-info/LICENSE
ellapycount-0.1.0.dist-info/METADATA
ellapycount-0.1.0.dist-info/WHEEL
ellapycount-0.1.0.dist-info/RECORD
